configen/__init__.py
configen/config.py
configen/configen.py
configen/samples/__init__.py
configen/samples/my_module.py
configen/templates/module.j2
configen/templates/sample_config.yaml
configen/utils.py
neoconfigen-2.5.0.dist-info/METADATA
neoconfigen-2.5.0.dist-info/WHEEL
neoconfigen-2.5.0.dist-info/entry_points.txt
neoconfigen-2.5.0.dist-info/RECORD
