Metadata-Version: 2.1
Name: neoconfigen
Version: 2.5.0
Summary: A fork of hydra-core's configen with extended type-compatibility.
Home-page: https://github.com/predictive-analytics-lab/neoconfigen
License: MIT
Keywords: hydra,python
Author: Omry Yadan
Requires-Python: >=3.10,<3.13
Classifier: License :: OSI Approved :: Apache Software License
Classifier: License :: OSI Approved :: MIT License
Classifier: Operating System :: OS Independent
Classifier: Programming Language :: Python :: 3
Classifier: Programming Language :: Python :: 3.10
Classifier: Programming Language :: Python :: 3.11
Classifier: Programming Language :: Python :: 3.12
Classifier: Typing :: Typed
Requires-Dist: hydra-core (>=1.2.0,<2.0.0)
Requires-Dist: jinja2 (>=3.0.3,<4.0.0)
Requires-Dist: markupsafe
Requires-Dist: typing-inspect (>=0.7.1,<0.8.0)
Project-URL: Repository, https://github.com/predictive-analytics-lab/neoconfigen
